setup.py
asd/__init__.py
asd/config.py
asd/custom_completion_finder.py
asd/json_browser.py
asd/openvpn_config_schema.py
asd/openvpn_manage.py
asd/register.py
asd/system_config.py
asd/tool.py
asd/tool_install.py
asd.egg-info/PKG-INFO
asd.egg-info/SOURCES.txt
asd.egg-info/dependency_links.txt
asd.egg-info/requires.txt
asd.egg-info/top_level.txt
bin/asd