Metadata-Version: 1.0
Name: asd
Version: 1.3.2
Summary: Various command line helper scripts`
Home-page: https://github.com/voidpp/asd.git
Author: Lajos Santa
Author-email: santa.lajos@coldline.hu
License: UNKNOWN
Platform: UNKNOWN
